pyscal3.libs/libgcc_s-8b50eaaa.so.1
pyscal3.libs/libstdc++-8baf04f9.so.6.0.28
pyscal3-3.2.7.data/headers/system.h
pyscal3/misc.py
pyscal3/entropy.cpp
pyscal3/cna.cpp
pyscal3/visualization.py
pyscal3/sh.cpp
pyscal3/__init__.py
pyscal3/attributes.py
pyscal3/traj_process.py
pyscal3/core.py
pyscal3/centrosymmetry.cpp
pyscal3/csl.py
pyscal3/csystem.cpython-38-i386-linux-gnu.so
pyscal3/voronoi.cpp
pyscal3/grain_boundary.py
pyscal3/trajectory.py
pyscal3/routines.py
pyscal3/solids.cpp
pyscal3/system_binding.cpp
pyscal3/atoms.py
pyscal3/structure_creator.py
pyscal3/neighbor.cpp
pyscal3/operations/entropy.py
pyscal3/operations/__init__.py
pyscal3/operations/voronoi.py
pyscal3/operations/identify.py
pyscal3/operations/chemical.py
pyscal3/operations/neighbor.py
pyscal3/operations/visualize.py
pyscal3/operations/input.py
pyscal3/operations/symmetry.py
pyscal3/operations/centrosymmetry.py
pyscal3/operations/cna.py
pyscal3/operations/calculations.py
pyscal3/operations/serialize.py
pyscal3/operations/operations.py
pyscal3/formats/__init__.py
pyscal3/formats/lammps.py
pyscal3/formats/mdtraj.py
pyscal3/formats/ase.py
pyscal3/formats/vasp.py
pyscal3/data/annotations.yaml
pyscal3/data/element_data.yaml
pyscal3/data/structure_data.yaml
pyscal3-3.2.7.dist-info/RECORD
pyscal3-3.2.7.dist-info/top_level.txt
pyscal3-3.2.7.dist-info/LICENSE
pyscal3-3.2.7.dist-info/WHEEL
pyscal3-3.2.7.dist-info/METADATA
