Metadata-Version: 2.1
Name: pyscal3
Version: 3.2.7
Summary: Python library written in C++ for calculation of local atomic structural environment
Home-page: https://pyscal.org
Download-URL: https://anaconda.org/conda-forge/pyscal
Author: Sarath Menon
Author-email: sarath.menon@pyscal.org
Classifier: Programming Language :: Python :: 3
License-File: LICENSE
Requires-Dist: pybind11
Requires-Dist: numpy
Requires-Dist: ase
Requires-Dist: pyyaml
